Metadata-Version: 1.0
Name: mamescraper
Version: 0.4
Summary: scrap mame games information and images
Home-page: https://github.com/pdrb/mamescraper
Author: Pedro Buteri Gonring
Author-email: pedro@bigode.net
License: MIT
Keywords: mame scraper games roms emulationstation retropie recalbox
Platform: UNKNOWN
